odoo/addons/project_duplicate_subtask/README.rst
odoo/addons/project_duplicate_subtask/__init__.py
odoo/addons/project_duplicate_subtask/__manifest__.py
odoo/addons/project_duplicate_subtask/i18n/es.po
odoo/addons/project_duplicate_subtask/i18n/es_AR.po
odoo/addons/project_duplicate_subtask/i18n/it.po
odoo/addons/project_duplicate_subtask/i18n/project_duplicate_subtask.pot
odoo/addons/project_duplicate_subtask/models/__init__.py
odoo/addons/project_duplicate_subtask/models/project_task.py
odoo/addons/project_duplicate_subtask/readme/CONTRIBUTORS.rst
odoo/addons/project_duplicate_subtask/readme/DESCRIPTION.rst
odoo/addons/project_duplicate_subtask/readme/USAGE.rst
odoo/addons/project_duplicate_subtask/static/description/icon.png
odoo/addons/project_duplicate_subtask/static/description/index.html
odoo/addons/project_duplicate_subtask/tests/__init__.py
odoo/addons/project_duplicate_subtask/tests/test_project_duplicate_subtask.py
odoo/addons/project_duplicate_subtask/views/project_duplicate_action.xml
odoo14_addon_project_duplicate_subtask-14.0.1.0.1.dev10.dist-info/METADATA
odoo14_addon_project_duplicate_subtask-14.0.1.0.1.dev10.dist-info/WHEEL
odoo14_addon_project_duplicate_subtask-14.0.1.0.1.dev10.dist-info/top_level.txt
odoo14_addon_project_duplicate_subtask-14.0.1.0.1.dev10.dist-info/RECORD
