Metadata-Version: 2.1
Name: odoo14-addon-project-duplicate-subtask
Version: 14.0.1.0.1.dev10
Summary: The module adds an action to duplicate tasks with the child subtasks
Home-page: https://github.com/OCA/project
Author: Forgeflow, Odoo Community Association (OCA)
Author-email: support@odoo-community.org
License: AGPL-3
Platform: UNKNOWN
Classifier: Programming Language :: Python
Classifier: Framework :: Odoo
Classifier: Framework :: Odoo :: 14.0
Classifier: License :: OSI Approved :: GNU Affero General Public License v3
Requires-Python: >=3.6
Requires-Dist: odoo <14.1dev,>=14.0a
